design.sv
module ram(
    input clk,
    input write_enable,
    input [9:0]address,
    input [7:0]data_in,
    output reg [7:0]data_out
);

reg [7:0]ram_block[0:1023];

always @(posedge clk) begin
        if(write_enable)
            ram_block[address] <= data_in;
        else
            data_out <= ram_block[address];
end

endmodule

testbench.sv
module ram_tb;

reg clk;
reg write_enable;
reg [9:0]address;
reg [7:0]data_in;
wire [7:0]data_out;

ram uut(clk,write_enable,address,data_in,data_out);

initial begin
  $dumpfile("ram.vcd");
  $dumpvars;
clk = 0;
data_in = 8'h56;
write_enable = 0;
address = 55;
#20
write_enable = 1;
#20;
write_enable = 0;
address = 66;
data_in = 8'h36;
#20
write_enable = 1;
#20 
write_enable = 0;
#20
address = 55;
#20
$finish();

end

always #10 clk = ~clk;  //clock generation

endmodule

ram.vcd
$date
	Wed Jul  9 06:20:27 2025
$end
$version
	Icarus Verilog
$end
$timescale
	1s
$end
$scope module ram_tb $end
$var wire 8 ! data_out [7:0] $end
$var reg 10 " address [9:0] $end
$var reg 1 # clk $end
$var reg 8 $ data_in [7:0] $end
$var reg 1 % write_enable $end
$scope module uut $end
$var wire 10 & address [9:0] $end
$var wire 1 # clk $end
$var wire 8 ' data_in [7:0] $end
$var wire 1 % write_enable $end
$var reg 8 ( data_out [7:0] $end
$upscope $end
$upscope $end
$enddefinitions $end
$comment Show the parameter values. $end
$dumpall
$end
#0
$dumpvars
bx (
b1010110 '
b110111 &
0%
b1010110 $
0#
b110111 "
bx !
$end
#10
1#
#20
0#
1%
#30
1#
#40
0#
b110110 $
b110110 '
b1000010 "
b1000010 &
0%
#50
1#
#60
0#
1%
#70
1#
#80
0#
0%
#90
b110110 !
b110110 (
1#
#100
0#
b110111 "
b110111 &
#110
b1010110 !
b1010110 (
1#
